{"name":"LUCY LAPPLEY","description":"With more ideas than you can shake a stick at, Lucy has a keen nose for creative juices and always finds the core USP of any business. She won’t stop until she’s wowed her crowd and smelt out that secret sauce.","image":"https://github.com/wolvesofwallstreet/wolves.assets.low/raw/main/cards/bois/level1/LUCY-300.jpg","external_url":"https://app.wolvesofwallstreet.finance/detail?type=bois&levelId=0&cardId=lucy","localization":{"uri":"./0003_{locale}.json","default":"en_US","locales":["en_US","zh_CN"]}}